dtbell/__init__.py
dtbell/__main__.py
dtbell/app.py
dtbell/cache.py
dtbell/config.py
dtbell/feed.py
dtbell/default/config.ini
dtbell/default/thumbnail.png
dtbell/default/urls
dtbell/handlers/__init__.py
dtbell/handlers/notification_handler.py
dtbell-1.1.1.dist-info/METADATA
dtbell-1.1.1.dist-info/WHEEL
dtbell-1.1.1.dist-info/entry_points.txt
dtbell-1.1.1.dist-info/licenses/LICENSE
dtbell-1.1.1.dist-info/RECORD
