Metadata-Version: 2.1
Name: dtbell
Version: 1.1.1
Summary: A highly configurable desktop notifier for RSS/Atom feeds.
Project-URL: Homepage, https://github.com/EscherMoore/DitchTheBell
Project-URL: repository, https://github.com/EscherMoore/DitchTheBell
Project-URL: Bug Tracker, https://github.com/EscherMoore/DitchTheBell/issues
Project-URL: Documentation, https://github.com/EscherMoore/DitchTheBell/blob/main/README.md
Author: Escher Moore
License-Expression: GPL-3.0-or-later
License-File: LICENSE
Keywords: atom,desktop,linux,notifications,notify,rss
Classifier: Intended Audience :: End Users/Desktop
Classifier: License :: OSI Approved :: GNU General Public License v3 or later (GPLv3+)
Classifier: Operating System :: POSIX :: Linux
Classifier: Programming Language :: Python :: 3
Classifier: Programming Language :: Python :: 3 :: Only
Classifier: Programming Language :: Python :: 3.7
Classifier: Programming Language :: Python :: 3.8
Classifier: Programming Language :: Python :: 3.9
Classifier: Programming Language :: Python :: 3.10
Classifier: Programming Language :: Python :: 3.11
Classifier: Topic :: Desktop Environment
Classifier: Topic :: Desktop Environment :: Window Managers
Classifier: Topic :: Desktop Environment :: Window Managers :: Applets
Classifier: Topic :: Internet :: WWW/HTTP
Classifier: Topic :: Internet :: WWW/HTTP :: Dynamic Content :: News/Diary
Classifier: Topic :: Internet :: WWW/HTTP :: Indexing/Search
Classifier: Topic :: Utilities
Requires-Python: >=3.7
Requires-Dist: aiohttp
Requires-Dist: feedparser
Requires-Dist: pydbus
Requires-Dist: pygobject
Requires-Dist: python-dateutil
Requires-Dist: pytz
